browsr/__about__.py
browsr/__init__.py
browsr/__main__.py
browsr/base.py
browsr/browsr.css
browsr/browsr.py
browsr/cli.py
browsr/config.py
browsr/exceptions.py
browsr/utils.py
browsr/screens/__init__.py
browsr/screens/code_browser.py
browsr/widgets/__init__.py
browsr/widgets/code_browser.py
browsr/widgets/confirmation.py
browsr/widgets/double_click_directory_tree.py
browsr/widgets/files.py
browsr/widgets/universal_directory_tree.py
browsr/widgets/vim.py
browsr/widgets/windows.py
browsr-1.22.1.dist-info/METADATA
browsr-1.22.1.dist-info/WHEEL
browsr-1.22.1.dist-info/entry_points.txt
browsr-1.22.1.dist-info/licenses/LICENSE
browsr-1.22.1.dist-info/RECORD
