Metadata-Version: 2.4
Name: browsr
Version: 1.22.1
Summary: TUI File Browser App
Project-URL: Documentation, https://github.com/juftin/browsr#readme
Project-URL: Issues, https://github.com/juftin/browsr/issues
Project-URL: Source, https://github.com/juftin/browsr
Author-email: Justin Flannery <juftin@juftin.com>
License-Expression: MIT
License-File: LICENSE
Classifier: Development Status :: 4 - Beta
Classifier: Operating System :: OS Independent
Classifier: Programming Language :: Python
Classifier: Programming Language :: Python :: 3.9
Classifier: Programming Language :: Python :: 3.10
Classifier: Programming Language :: Python :: 3.11
Classifier: Programming Language :: Python :: 3.12
Classifier: Programming Language :: Python :: 3.13
Classifier: Programming Language :: Python :: Implementation :: CPython
Classifier: Programming Language :: Python :: Implementation :: PyPy
Requires-Python: <4.0,>=3.9
Requires-Dist: art~=6.5
Requires-Dist: click~=8.1.7
Requires-Dist: pandas<3,>2
Requires-Dist: pillow>=11.3.0
Requires-Dist: pymupdf~=1.26.3
Requires-Dist: pyperclip~=1.9.0
Requires-Dist: rich-click~=1.8.9
Requires-Dist: rich-pixels~=3.0.1
Requires-Dist: rich<15,>=14
Requires-Dist: textual-universal-directorytree~=1.6.0
Requires-Dist: textual<6,>=5
Requires-Dist: universal-pathlib~=0.2.6
Provides-Extra: all
Requires-Dist: pyarrow~=21.0.0; extra == 'all'
Requires-Dist: textual-universal-directorytree[remote]~=1.6.0; extra == 'all'
Provides-Extra: data
Requires-Dist: pyarrow~=21.0.0; extra == 'data'
Provides-Extra: parquet
Requires-Dist: pyarrow~=21.0.0; extra == 'parquet'
Provides-Extra: remote
Requires-Dist: textual-universal-directorytree[remote]~=1.6.0; extra == 'remote'
